pyrobosim/__init__.py
pyrobosim/core/__init__.py
pyrobosim/core/dynamics.py
pyrobosim/core/gazebo.py
pyrobosim/core/hallway.py
pyrobosim/core/locations.py
pyrobosim/core/objects.py
pyrobosim/core/robot.py
pyrobosim/core/room.py
pyrobosim/core/types.py
pyrobosim/core/world.py
pyrobosim/core/yaml_utils.py
pyrobosim/data/.gitignore
pyrobosim/data/example_location_data.yaml
pyrobosim/data/example_location_data_accessories.yaml
pyrobosim/data/example_location_data_furniture.yaml
pyrobosim/data/example_object_data.yaml
pyrobosim/data/example_object_data_drink.yaml
pyrobosim/data/example_object_data_food.yaml
pyrobosim/data/pddlstream_simple_world.yaml
pyrobosim/data/roscon_2024_location_data.yaml
pyrobosim/data/roscon_2024_object_data.yaml
pyrobosim/data/roscon_2024_workshop_world.yaml
pyrobosim/data/test_world.yaml
pyrobosim/data/test_world_multirobot.yaml
pyrobosim/data/pddlstream/domains/01_simple/domain.pddl
pyrobosim/data/pddlstream/domains/01_simple/streams.pddl
pyrobosim/data/pddlstream/domains/02_derived/domain.pddl
pyrobosim/data/pddlstream/domains/02_derived/streams.pddl
pyrobosim/data/pddlstream/domains/03_nav_stream/domain.pddl
pyrobosim/data/pddlstream/domains/03_nav_stream/streams.pddl
pyrobosim/data/pddlstream/domains/04_nav_manip_stream/domain.pddl
pyrobosim/data/pddlstream/domains/04_nav_manip_stream/streams.pddl
pyrobosim/data/pddlstream/domains/05_nav_grasp_stream/domain.pddl
pyrobosim/data/pddlstream/domains/05_nav_grasp_stream/streams.pddl
pyrobosim/data/pddlstream/domains/06_open_close_detect/domain.pddl
pyrobosim/data/pddlstream/domains/06_open_close_detect/streams.pddl
pyrobosim/data/sample_models/coke_can/model-1_2.sdf
pyrobosim/data/sample_models/coke_can/model-1_3.sdf
pyrobosim/data/sample_models/coke_can/model-1_4.sdf
pyrobosim/data/sample_models/coke_can/model.config
pyrobosim/data/sample_models/coke_can/model.sdf
pyrobosim/data/sample_models/coke_can/materials/textures/coke_can.png
pyrobosim/data/sample_models/coke_can/meshes/coke_can.dae
pyrobosim-4.3.3.dist-info/METADATA
pyrobosim-4.3.3.dist-info/WHEEL
pyrobosim-4.3.3.dist-info/top_level.txt
pyrobosim-4.3.3.dist-info/zip-safe
pyrobosim-4.3.3.dist-info/RECORD
