Metadata-Version: 2.4
Name: pyrobosim
Version: 4.3.3
Summary: ROS 2 enabled 2D mobile robot simulator for behavior prototyping.
Home-page: https://github.com/sea-bass/pyrobosim
Author: Sebastian Castro
Author-email: sebas.a.castro@gmail.com
License: MIT
Requires-Dist: adjustText
Requires-Dist: astar
Requires-Dist: matplotlib
Requires-Dist: numpy
Requires-Dist: pycollada
Requires-Dist: PySide6>=6.4.0
Requires-Dist: PyYAML
Requires-Dist: shapely>=2.0.1
Requires-Dist: scipy
Requires-Dist: transforms3d
Requires-Dist: trimesh
Requires-Dist: typing_extensions
Dynamic: author
Dynamic: author-email
Dynamic: description
Dynamic: description-content-type
Dynamic: home-page
Dynamic: license
Dynamic: requires-dist
Dynamic: summary
